klaxon/__init__.py
klaxon/configuration.py
klaxon/exceptions.py
klaxon/invoke.py
klaxon/main.py
klaxon-1.1.1.dist-info/entry_points.txt
klaxon-1.1.1.dist-info/LICENSE.txt
klaxon-1.1.1.dist-info/WHEEL
klaxon-1.1.1.dist-info/METADATA
klaxon-1.1.1.dist-info/RECORD
