Metadata-Version: 2.1
Name: klaxon
Version: 1.1.1
Summary: Use osascript to send notifications.
Home-page: https://pypi.org/project/klaxon/
License: Apache-2.0
Keywords: mac,notifications,productivity
Author: Stephan Fitzpatrick
Author-email: knowsuchagency@gmail.com
Requires-Python: >=3.6,<4.0
Classifier: License :: OSI Approved :: Apache Software License
Classifier: Programming Language :: Python :: 3
Classifier: Programming Language :: Python :: 3.6
Classifier: Programming Language :: Python :: 3.7
Classifier: Programming Language :: Python :: 3.8
Provides-Extra: notifiers
Requires-Dist: notifiers (>=1.0,<2.0); extra == "notifiers"
Requires-Dist: toml (>=0.10.0,<0.11.0)
Project-URL: Repository, https://github.com/knowsuchagency/klaxon
